mvsdk/__init__.py
mvsdk/api/__init__.py
mvsdk/rest/__init__.py
mvsdk/rest/asset/__init__.py
mvsdk/rest/connect/__init__.py
mvsdk/rest/keyword/__init__.py
MediaValet_SDK-0.0.4.dist-info/METADATA
MediaValet_SDK-0.0.4.dist-info/WHEEL
MediaValet_SDK-0.0.4.dist-info/top_level.txt
MediaValet_SDK-0.0.4.dist-info/RECORD
