Metadata-Version: 2.1
Name: MediaValet-SDK
Version: 0.0.4
Summary: MediaValet Python SDK
Home-page: https://github.com/armstro-ca/mvsdk
Author: James Armstrong
Author-email: j@armstro.ca
License: MIT
Project-URL: Bug Tracker, https://github.com/armstro-ca/mvsdk/issues
Requires-Dist: requests
